{
  "name": "emitter-chat",
  "version": "1.0.0",
  "description": "A simple socket.io chat app",
  "main": "index.js",
  "dependencies": {
    "express": "^4.16.3",
    "lodash": "^4.17.10",
    "react": "^16.4.2",
    "react-dom": "^15.6.2",
    "react-facebook-login": "^4.0.1",
    "react-google-login": "^3.2.1",
    "react-icons": "^3.0.5",
    "react-scripts": "^1.1.4",
    "socket.io": "^2.1.1",
    "uuid": "^3.3.2"
  },
  "devDependencies": {},
  "scripts": {
    "start": "node src/server/index.js",
    "dev": "concurrently 'npm run react' 'npm run server'",
    "react": "react-scripts start",
    "server": "nodemon src/server/index.js",
    "build": "react-scripts build",
    "heroku-postbuild": "npm run build",
    "test": "react-scripts test --env=jsdom",
    "eject": "react-scripts eject",
    "styles": "cp ../../react-chat-app/src/styles/index.css* ./src/"
  },
  "repository": {
    "type": "git",
    "url": "git+https://github.com/mchaffin/emitter-chat.git"
  },
  "author": "Mark Chaffin",
  "license": "ISC",
  "bugs": {
    "url": "https://github.com/mchaffin/emitter-chat/issues"
  },
  "homepage": "https://github.com/mchaffin/emitter-chat#readme"
}
